vup/__init__.py
vup/generate.py
vup/init.py
vup/main.py
vup/setting.py
vup/update.py
vup-1.1.4.dist-info/LICENSE
vup-1.1.4.dist-info/METADATA
vup-1.1.4.dist-info/WHEEL
vup-1.1.4.dist-info/entry_points.txt
vup-1.1.4.dist-info/top_level.txt
vup-1.1.4.dist-info/RECORD
