Metadata-Version: 2.1
Name: vup
Version: 1.1.4
Summary: VUP: Version UPdater: Version management system
Home-page: https://github.com/SiLeader/vup
Author: SiLeader
License: GPLv3.0
Platform: UNKNOWN
Classifier: Environment :: Console
Classifier: License :: OSI Approved
Classifier: License :: OSI Approved :: GNU General Public License v3 (GPLv3)
Classifier: License :: OSI Approved :: GNU General Public License v3 or later (GPLv3+)
Classifier: Topic :: Software Development
Classifier: Topic :: Software Development :: Code Generators
